m3u_filter/__init__.py
m3u_filter/channel_tree.py
m3u_filter/download_worker.py
m3u_filter/embedded_vlc.py
m3u_filter/gui.py
m3u_filter/icon_cache.py
m3u_filter/import_source_dialog.py
m3u_filter/m3u_downloader.py
m3u_filter/m3u_handler.py
m3u_filter/m3u_server.py
m3u_filter/main.py
m3u_filter/progress_widget.py
m3u_filter/vlc_manager.py
m3u_filter-0.1.0.dist-info/LICENSE
m3u_filter-0.1.0.dist-info/METADATA
m3u_filter-0.1.0.dist-info/WHEEL
m3u_filter-0.1.0.dist-info/entry_points.txt
m3u_filter-0.1.0.dist-info/top_level.txt
m3u_filter-0.1.0.dist-info/RECORD
