Metadata-Version: 2.1
Name: m3u-filter
Version: 0.1.0
Summary: A GUI application to open or download, filter and manage M3U playlists.
Home-page: https://github.com/ko_dez/m3u-filter
Author: Morgan Tørvolt
Author-email: morgan@torvolt.com
Classifier: Programming Language :: Python :: 3
Classifier: License :: OSI Approved :: GNU General Public License v3 (GPLv3)
Classifier: Operating System :: OS Independent
Classifier: Operating System :: Microsoft :: Windows
Classifier: Operating System :: POSIX :: Linux
Classifier: Operating System :: MacOS
Classifier: Environment :: X11 Applications :: Qt
Classifier: Environment :: Win32 (MS Windows)
Requires-Python: >=3.8
License-File: LICENSE
Requires-Dist: PyQt5 >=5.15.0
Requires-Dist: requests >=2.25.0
Requires-Dist: python-vlc >=3.0.0
Requires-Dist: psutil >=5.8.0
